{
"type": "FeatureCollection",
"name": "Archives_new",
"crs": { "type": "name", "properties": { "name": "urn:ogc:def:crs:OGC:1.3:CRS84" } },
"features": [
{ "type": "Feature", "properties": { "id": "node/10280670340", "@id": "node/10280670340", "addr:city": null, "addr:housenumber": null, "addr:postcode": null, "addr:street": "Jalan Sirsak No.67, RT.1/RW.2, Jagakarsa, Kecamatan Jagakarsa, Kota Jakarta Selatan, Daerah Khusus Ibukota Jakarta", "amenity": "archive", "amenity_1": null, "area": null, "building": null, "building:levels": null, "description": null, "government": null, "layer": null, "name": "Gedung Arsip PT PLN (Persero)", "office": null, "opening_hours": "Belum diketahui", "operator": "Tidak Terdefinisi", "operator:type": null, "phone": null, "phone:mobile": "0217261122", "postal_code": null, "tactile_paving": null, "website": "https://www.pln.co.id/", "wheelchair": null, "wikidata": "Q115796374", "wikipedia:en": null, "Alamat": "Jalan Sirs" }, "geometry": { "type": "Point", "coordinates": [ 106.8186683, -6.3374736 ] } },
{ "type": "Feature", "properties": { "id": "node/10285473553", "@id": "node/10285473553", "addr:city": null, "addr:housenumber": null, "addr:postcode": null, "addr:street": "Kebondalem, Purwokerto Lor, Kecamatan Purwokerto Timur, Kabupaten Banyumas, Jawa Tengah 53116", "amenity": "archive", "amenity_1": null, "area": null, "building": null, "building:levels": null, "description": null, "government": null, "layer": null, "name": "Gedung Arsip Kabupaten Banyumas", "office": null, "opening_hours": "Belum diketahui", "operator": "Tidak Terdefinisi", "operator:type": null, "phone": null, "phone:mobile": null, "postal_code": null, "tactile_paving": null, "website": null, "wheelchair": null, "wikidata": "Q115861837", "wikipedia:en": null, "Alamat": "Kebondalem" }, "geometry": { "type": "Point", "coordinates": [ 109.2411443, -7.422029 ] } }
]
}
